aladhan/__init__.py
aladhan/__main__.py
aladhan/client.py
aladhan/data_classes.py
aladhan/endpoints.py
aladhan/enums.py
aladhan/exceptions.py
aladhan/http.py
aladhan/methods.py
aladhan/types.py
aladhan_py-1.2.2.dist-info/licenses/LICENSE
aladhan_py-1.2.2.dist-info/METADATA
aladhan_py-1.2.2.dist-info/WHEEL
aladhan_py-1.2.2.dist-info/top_level.txt
aladhan_py-1.2.2.dist-info/RECORD
