Metadata-Version: 2.4
Name: aladhan.py
Version: 1.2.2
Summary: A Python wrapper for the Aladhan prayer times API
Home-page: https://github.com/HETHAT/aladhan.py
Author: HETHAT
Author-email: zhethat@gmail.com
License: MIT
Project-URL: Documentation, https://aladhanpy.rtfd.org 
Project-URL: Issue tracker, https://github.com/HETHAT/aladhan.py/issues
Classifier: License :: OSI Approved :: MIT License
Classifier: Intended Audience :: Developers
Classifier: Natural Language :: English
Classifier: Operating System :: OS Independent
Classifier: Programming Language :: Python
Classifier: Programming Language :: Python :: 3
Classifier: Programming Language :: Python :: 3 :: Only
Classifier: Programming Language :: Python :: 3.7
Classifier: Programming Language :: Python :: 3.8
Classifier: Programming Language :: Python :: 3.9
Classifier: Programming Language :: Python :: 3.10
Classifier: Topic :: Internet
Classifier: Topic :: Software Development :: Libraries
Classifier: Topic :: Software Development :: Libraries :: Python Modules
Classifier: Topic :: Utilities
Requires-Python: >=3.7
License-File: LICENSE
Requires-Dist: aiohttp
Requires-Dist: pytz
Requires-Dist: requests
Provides-Extra: dev
Requires-Dist: flake8; extra == "dev"
Requires-Dist: pytest==6.2.4; extra == "dev"
Requires-Dist: pytest-asyncio==0.15.1; extra == "dev"
Requires-Dist: pytest-cov==2.12.1; extra == "dev"
Requires-Dist: pytest-mock; extra == "dev"
Dynamic: author
Dynamic: author-email
Dynamic: classifier
Dynamic: description
Dynamic: description-content-type
Dynamic: home-page
Dynamic: license
Dynamic: license-file
Dynamic: project-url
Dynamic: provides-extra
Dynamic: requires-dist
Dynamic: requires-python
Dynamic: summary
